mqtt_exporter/__init__.py
mqtt_exporter/__main__.py
mqtt_exporter/exceptions.py
mqtt_exporter/main.py
mqtt_exporter/settings.py
mqtt_exporter-1.9.0.dist-info/licenses/LICENSE
mqtt_exporter-1.9.0.dist-info/METADATA
mqtt_exporter-1.9.0.dist-info/WHEEL
mqtt_exporter-1.9.0.dist-info/entry_points.txt
mqtt_exporter-1.9.0.dist-info/top_level.txt
mqtt_exporter-1.9.0.dist-info/RECORD
