Metadata-Version: 2.4
Name: mqtt-exporter
Version: 1.9.0
Summary: Simple generic MQTT Prometheus exporter for IoT working out of the box
Author-email: Kevin Petremann <kpetrem@gmail.com>
License: MIT License
Project-URL: Homepage, https://github.com/kpetremann/mqtt-exporter
Keywords: iot,mqtt,prometheus
Classifier: Development Status :: 5 - Production/Stable
Classifier: License :: OSI Approved :: MIT License
Classifier: Programming Language :: Python :: 3
Classifier: Programming Language :: Python :: 3.10
Classifier: Programming Language :: Python :: 3.11
Classifier: Programming Language :: Python :: 3.12
License-File: LICENSE
Requires-Dist: paho-mqtt==2.1.0
Requires-Dist: prometheus-client==0.22.1
Dynamic: license-file
